cli.py
create_lillie-12.0.1.dist-info/METADATA
create_lillie-12.0.1.dist-info/WHEEL
create_lillie-12.0.1.dist-info/entry_points.txt
create_lillie-12.0.1.dist-info/top_level.txt
create_lillie-12.0.1.dist-info/RECORD
