Metadata-Version: 2.4
Name: create-lillie
Version: 12.0.1
Summary: A CLI tool for creating lilliepy projects
Home-page: https://github.com/websitedeb/create-lillie
Author: sarthak ghoshal
Author-email: sarthak22.ghoshal@gmail.com
Keywords: reactpy,lilliepy,create-lillie,create-lilliepy
Classifier: Programming Language :: Python :: 3
Classifier: License :: OSI Approved :: MIT License
Classifier: Operating System :: OS Independent
Requires-Python: >=3.7
Requires-Dist: typer[all]
Requires-Dist: colorama
Dynamic: author
Dynamic: author-email
Dynamic: classifier
Dynamic: description
Dynamic: description-content-type
Dynamic: home-page
Dynamic: keywords
Dynamic: requires-dist
Dynamic: requires-python
Dynamic: summary
